{
    "azimuth": {
        "angle": {
            "start": 0,
            "end": 360,
            "frequency": 25,
            "delta": 0.1
        },
        "value": {
            "start": 20,
            "end": 50,
            "frequency": 50,
            "delta": 1
        },
        "targetAngle": {
            "start": 0,
            "end": 360,
            "frequency": 3000,
            "delta": 25
        }
    },
    "speedometer": {
        "value": {
            "start": 5,
            "end": 15,
            "frequency": 80,
            "delta": 0.1
        }
    },
    "cog": {
        "heading": {
            "start": 260,
            "end": 290,
            "frequency": 40,
            "delta": 0.1
        },
        "courseOverGround": {
            "start": 285,
            "end": 295,
            "frequency": 50,
            "delta": 0.1
        }
    },
    "rudder": {
        "rudderSetPointAngle": {
            "start": -50,
            "end": 50,
            "frequency": 1000,
            "delta": 5
        },
        "rudderAngle": {
            "start": -50,
            "end": 50,
            "frequency": 1200,
            "delta": 5
        }
    }
}